{
  "reports": {
    "2026-06-04": {
      "date": "2026年6月4日",
      "idioms": [
        {"idiom": "等量齐观", "explanation": "对有差别的事物同等看待", "focus": "比较分析类论述"},
        {"idiom": "责无旁贷", "explanation": "自己应尽的责任，不能推卸给别人", "focus": "责任担当类表述"},
        {"idiom": "有声有色", "explanation": "形容说话或表演精彩生动", "focus": "形容工作成效显著"},
        {"idiom": "触类旁通", "explanation": "掌握了某一事物的规律，就能推知同类事物", "focus": "学习方法、知识迁移"},
        {"idiom": "诲人不倦", "explanation": "耐心教导别人，不知疲倦", "focus": "教育话题"},
        {"idiom": "人头攒动", "explanation": "形容人很多，频繁移动的热闹场面", "focus": "场景描写"},
        {"idiom": "车水马龙", "explanation": "车如流水，马如游龙，形容繁华热闹景象", "focus": "城市繁荣、经济活跃"},
        {"idiom": "目无全牛", "explanation": "比喻技艺达到极其纯熟的地步", "focus": "工匠精神、专业能力"},
        {"idiom": "相辅相成", "explanation": "两件事物互相配合，互相辅助，缺一不可", "focus": "多方协作论述"},
        {"idiom": "居安思危", "explanation": "处于安乐时想到可能出现的危险", "focus": "忧患意识、底线思维"}
      ],
      "knowledge": [
        {
          "category": "科技时政",
          "title": "长征十二号乙运载火箭首飞成功",
          "body": "2026年6月1日，长征十二号乙运载火箭首飞成功，这是我国目前运力最大的单芯级火箭。区别于长征五号（大型捆绑式），「单芯级」意味着无需捆绑助推器，代表我国火箭构型技术的重大突破。",
          "exam_point": "运力最大的单芯级火箭 = 长征十二号乙（2026.6）。对比：长征五号是捆绑式。"
        },
        {
          "category": "法律常识",
          "title": "2026国考：常识判断与政治理论已拆分",
          "body": "2026年国考大纲将「政治理论」独立为单独模块。常识判断现覆盖六大领域：经济、文化、社会、生态、法律、科技。其中法律占比最高（约35%），命题风格从「法条记忆」转向「案例推导」。",
          "exam_point": "常识判断不含政治理论（2026起已拆分）。重点法律：宪法、行政法、监察法、反洗钱法（2026新修）。"
        },
        {
          "category": "时政",
          "title": "四大全球倡议速记",
          "body": "中国相继提出四大全球倡议：全球发展倡议（2021）、全球安全倡议（2022）、全球文明倡议（2023）、全球治理倡议（2025）。其中全球治理倡议是最新提出的。",
          "exam_point": "最新 = 全球治理倡议（2025）。口诀：「发安文治，一二三五」。"
        }
      ]
    }
  }
}
